networking_hpe/__init__.py
networking_hpe/_i18n.py
networking_hpe/managers.py
networking_hpe/bnpclient/__init__.py
networking_hpe/bnpclient/bnp_client_ext/__init__.py
networking_hpe/bnpclient/bnp_client_ext/shell.py
networking_hpe/bnpclient/bnp_client_ext/bnpcredential/__init__.py
networking_hpe/bnpclient/bnp_client_ext/bnpcredential/_bnp_credential.py
networking_hpe/bnpclient/bnp_client_ext/bnpswitch/__init__.py
networking_hpe/bnpclient/bnp_client_ext/bnpswitch/_bnp_switch.py
networking_hpe/bnpclient/bnp_client_ext/bnpswitch/_bnp_switchport.py
networking_hpe/bnpclient/bnp_client_ext/v2_0/__init__.py
networking_hpe/bnpclient/bnp_client_ext/v2_0/client.py
networking_hpe/common/__init__.py
networking_hpe/common/constants.py
networking_hpe/common/exceptions.py
networking_hpe/common/snmp_client.py
networking_hpe/common/validators.py
networking_hpe/db/__init__.py
networking_hpe/db/bm_nw_provision_db.py
networking_hpe/db/bm_nw_provision_models.py
networking_hpe/db/migration/__init__.py
networking_hpe/db/migration/alembic_migrations/README
networking_hpe/db/migration/alembic_migrations/__init__.py
networking_hpe/db/migration/alembic_migrations/env.py
networking_hpe/db/migration/alembic_migrations/script.py.mako
networking_hpe/db/migration/alembic_migrations/versions/CONTRACT_HEAD
networking_hpe/db/migration/alembic_migrations/versions/EXPAND_HEAD
networking_hpe/db/migration/alembic_migrations/versions/__init__.py
networking_hpe/db/migration/alembic_migrations/versions/start_networking_hpe.py
networking_hpe/db/migration/alembic_migrations/versions/pike/contract/9f1c0061fd83_initial.py
networking_hpe/db/migration/alembic_migrations/versions/pike/expand/06867195bc82_initial.py
networking_hpe/db/migration/models/__init__.py
networking_hpe/db/migration/models/head.py
networking_hpe/drivers/__init__.py
networking_hpe/drivers/port_provisioning_driver.py
networking_hpe/drivers/snmp_provisioning_driver.py
networking_hpe/ml2/__init__.py
networking_hpe-1.0.0.dist-info/DESCRIPTION.rst
networking_hpe-1.0.0.dist-info/METADATA
networking_hpe-1.0.0.dist-info/RECORD
networking_hpe-1.0.0.dist-info/WHEEL
networking_hpe-1.0.0.dist-info/entry_points.txt
networking_hpe-1.0.0.dist-info/metadata.json
networking_hpe-1.0.0.dist-info/pbr.json
networking_hpe-1.0.0.dist-info/top_level.txt
