Metadata-Version: 2.0
Name: networking-hpe
Version: 1.0.0
Summary: HPE mechanism drivers for bare metal connectivity
Home-page: http://www.openstack.org/
Author: OpenStack
Author-email: openstack-dev@lists.openstack.org
License: UNKNOWN
Platform: UNKNOWN
Classifier: Environment :: OpenStack
Classifier: Intended Audience :: Information Technology
Classifier: Intended Audience :: System Administrators
Classifier: License :: OSI Approved :: Apache Software License
Classifier: Operating System :: POSIX :: Linux
Classifier: Programming Language :: Python
Classifier: Programming Language :: Python :: 2
Classifier: Programming Language :: Python :: 2.7
Classifier: Programming Language :: Python :: 2.6
Classifier: Programming Language :: Python :: 3
Classifier: Programming Language :: Python :: 3.3
Classifier: Programming Language :: Python :: 3.4
Requires-Dist: pbr (!=2.1.0,>=2.0.0)
Requires-Dist: pysnmp (!=4.3.4,>=4.2.3,!=4.3.7,!=4.3.5,!=4.3.6)
Requires-Dist: python-neutronclient (>=6.3.0)
